m3u_serializer/__init__.py
m3u_serializer/exceptions.py
m3u_serializer/reader.py
m3u_serializer/record.py
m3u_serializer/util.py
m3u_serializer/version.py
m3u_serializer/writer.py
m3u_serializer-0.3.3.dist-info/LICENCE.md
m3u_serializer-0.3.3.dist-info/METADATA
m3u_serializer-0.3.3.dist-info/WHEEL
m3u_serializer-0.3.3.dist-info/top_level.txt
m3u_serializer-0.3.3.dist-info/RECORD
