Metadata-Version: 2.1
Name: m3u-serializer
Version: 0.3.3
Summary: M3U serializer/deserializer
Home-page: https://www.pe2mbs.nl/M3U_Serializer/
Author: Marc Bertens-Nguyen
Author-email: m.bertens@pe2mbs.nl
Maintainer: Marc Bertens-Nguyen
Maintainer-email: m.bertens@pe2mb2.nl
License: GNU General Public License, version 2 (only)
Project-URL: Documentation, https://github.com/pe2mbs/m3u_serializer/wiki
Project-URL: Source Code, https://github.com/pe2mbs/m3u_serializer/
Project-URL: Issue Tracker, https://github.com/pe2mbs/m3u_serializer/issues/
Classifier: Development Status :: 5 - Production/Stable
Classifier: Intended Audience :: Developers
Classifier: License :: OSI Approved :: GNU General Public License v2 (GPLv2)
Classifier: Operating System :: OS Independent
Classifier: Programming Language :: Python
Classifier: Topic :: Multimedia
Classifier: Topic :: Software Development :: Libraries
Classifier: Topic :: Software Development :: Libraries :: Python Modules
Classifier: Topic :: Scientific/Engineering :: Interface Engine/Protocol Translator
Requires-Python: >=3.6
License-File: LICENCE.md
Requires-Dist: requests
